django_payments_payu-2.0.0.dist-info/licenses/AUTHORS.rst
django_payments_payu-2.0.0.dist-info/licenses/LICENSE
payments_payu/__init__.py
payments_payu/provider.py
django_payments_payu-2.0.0.dist-info/METADATA
django_payments_payu-2.0.0.dist-info/WHEEL
django_payments_payu-2.0.0.dist-info/top_level.txt
django_payments_payu-2.0.0.dist-info/RECORD
